pyqt_dreamstudio/__init__.py
pyqt_dreamstudio/currentImageView.py
pyqt_dreamstudio/explorerWidget.py
pyqt_dreamstudio/imageListWidget.py
pyqt_dreamstudio/imageSqlite.py
pyqt_dreamstudio/imageStableDiffusionPage.py
pyqt_dreamstudio/inputDialog.py
pyqt_dreamstudio/leftSideBar.py
pyqt_dreamstudio/logo.png
pyqt_dreamstudio/main.py
pyqt_dreamstudio/notifier.py
pyqt_dreamstudio/rightSideBar.py
pyqt_dreamstudio/searchBar.py
pyqt_dreamstudio/svgButton.py
pyqt_dreamstudio/svgLabel.py
pyqt_dreamstudio/thumbnailView.py
pyqt_dreamstudio/toast.py
pyqt_dreamstudio/viewWidget.py
pyqt_dreamstudio/ico/__init__.py
pyqt_dreamstudio/ico/copy_light.svg
pyqt_dreamstudio/ico/history.svg
pyqt_dreamstudio/ico/save_light.svg
pyqt_dreamstudio/ico/setting.svg
pyqt_dreamstudio-0.0.12.dist-info/LICENSE
pyqt_dreamstudio-0.0.12.dist-info/METADATA
pyqt_dreamstudio-0.0.12.dist-info/WHEEL
pyqt_dreamstudio-0.0.12.dist-info/top_level.txt
pyqt_dreamstudio-0.0.12.dist-info/RECORD
