Metadata-Version: 2.1
Name: pyqt-dreamstudio
Version: 0.0.12
Summary: Using DreamStudio API in Python desktop application
Home-page: https://github.com/yjg30737/pyqt-dreamstudio.git
Author: Jung Gyu Yoon
Author-email: yjg30737@gmail.com
License: MIT
License-File: LICENSE
Requires-Dist: PyQt5 (>=5.14)
Requires-Dist: PySide6
Requires-Dist: qtpy
Requires-Dist: stability-sdk
